{
  "activities": [],
  "goals": {
    "activeMinutes": 25,
    "caloriesOut": 2800,
    "distance": 8,
    "floors": 10,
    "steps": 11500
  },
  "summary": {
    "activeScore": -1,
    "activityCalories": 1341,
    "caloriesBMR": 1741,
    "caloriesOut": 2808,
    "distances": [
      {
        "activity": "total",
        "distance": 5.82
      },
      {
        "activity": "tracker",
        "distance": 5.82
      },
      {
        "activity": "loggedActivities",
        "distance": 0
      },
      {
        "activity": "veryActive",
        "distance": 0
      },
      {
        "activity": "moderatelyActive",
        "distance": 0
      },
      {
        "activity": "lightlyActive",
        "distance": 5.8
      },
      {
        "activity": "sedentaryActive",
        "distance": 0
      }
    ],
    "elevation": 18.29,
    "fairlyActiveMinutes": 0,
    "floors": 6,
    "heartRateZones": [
      {
        "caloriesOut": 2321.664,
        "max": 93,
        "min": 30,
        "minutes": 1291,
        "name": "Out of Range"
      },
      {
        "caloriesOut": 388.87872,
        "max": 130,
        "min": 93,
        "minutes": 68,
        "name": "Fat Burn"
      },
      {
        "caloriesOut": 0,
        "max": 158,
        "min": 130,
        "minutes": 0,
        "name": "Cardio"
      },
      {
        "caloriesOut": 0,
        "max": 220,
        "min": 158,
        "minutes": 0,
        "name": "Peak"
      }
    ],
    "lightlyActiveMinutes": 308,
    "marginalCalories": 725,
    "restingHeartRate": 55,
    "sedentaryMinutes": 640,
    "steps": 7792,
    "veryActiveMinutes": 0
  }
}