{
  "activities": [],
  "goals": {
    "activeMinutes": 25,
    "caloriesOut": 2800,
    "distance": 8,
    "floors": 10,
    "steps": 11500
  },
  "summary": {
    "activeScore": -1,
    "activityCalories": 1337,
    "caloriesBMR": 1738,
    "caloriesOut": 2816,
    "distances": [
      {
        "activity": "total",
        "distance": 6.47
      },
      {
        "activity": "tracker",
        "distance": 6.47
      },
      {
        "activity": "loggedActivities",
        "distance": 0
      },
      {
        "activity": "veryActive",
        "distance": 0.73
      },
      {
        "activity": "moderatelyActive",
        "distance": 0.15
      },
      {
        "activity": "lightlyActive",
        "distance": 5.58
      },
      {
        "activity": "sedentaryActive",
        "distance": 0
      }
    ],
    "elevation": 39.62,
    "fairlyActiveMinutes": 3,
    "floors": 13,
    "heartRateZones": [
      {
        "caloriesOut": 2409.25089,
        "max": 93,
        "min": 30,
        "minutes": 1363,
        "name": "Out of Range"
      },
      {
        "caloriesOut": 387.84123,
        "max": 130,
        "min": 93,
        "minutes": 61,
        "name": "Fat Burn"
      },
      {
        "caloriesOut": 0,
        "max": 158,
        "min": 130,
        "minutes": 0,
        "name": "Cardio"
      },
      {
        "caloriesOut": 0,
        "max": 220,
        "min": 158,
        "minutes": 0,
        "name": "Peak"
      }
    ],
    "lightlyActiveMinutes": 287,
    "marginalCalories": 724,
    "restingHeartRate": 55,
    "sedentaryMinutes": 629,
    "steps": 8668,
    "veryActiveMinutes": 9
  }
}